omni_camera-0.6.3.dist-info/METADATA
omni_camera-0.6.3.dist-info/WHEEL
omni_camera-0.6.3.dist-info/licenses/LICENSE
omni_camera/__init__.py
omni_camera/omni_camera.pyd
omni_camera-0.6.3.dist-info/RECORD
